socketio/__init__.py
socketio/admin.py
socketio/asgi.py
socketio/async_admin.py
socketio/async_aiopika_manager.py
socketio/async_client.py
socketio/async_manager.py
socketio/async_namespace.py
socketio/async_pubsub_manager.py
socketio/async_redis_manager.py
socketio/async_server.py
socketio/async_simple_client.py
socketio/base_client.py
socketio/base_manager.py
socketio/base_namespace.py
socketio/base_server.py
socketio/client.py
socketio/exceptions.py
socketio/kafka_manager.py
socketio/kombu_manager.py
socketio/manager.py
socketio/middleware.py
socketio/msgpack_packet.py
socketio/namespace.py
socketio/packet.py
socketio/pubsub_manager.py
socketio/redis_manager.py
socketio/server.py
socketio/simple_client.py
socketio/tornado.py
socketio/zmq_manager.py
python_socketio-5.11.3.dist-info/LICENSE
python_socketio-5.11.3.dist-info/METADATA
python_socketio-5.11.3.dist-info/WHEEL
python_socketio-5.11.3.dist-info/top_level.txt
python_socketio-5.11.3.dist-info/RECORD
