Metadata-Version: 2.1
Name: python-socketio
Version: 5.11.3
Summary: Socket.IO server and client for Python
Author-email: Miguel Grinberg <miguel.grinberg@gmail.com>
Project-URL: Homepage, https://github.com/miguelgrinberg/python-socketio
Project-URL: Bug Tracker, https://github.com/miguelgrinberg/python-socketio/issues
Classifier: Environment :: Web Environment
Classifier: Intended Audience :: Developers
Classifier: Programming Language :: Python :: 3
Classifier: License :: OSI Approved :: MIT License
Classifier: Operating System :: OS Independent
Requires-Python: >=3.8
License-File: LICENSE
Requires-Dist: bidict>=0.21.0
Requires-Dist: python-engineio>=4.8.0
Provides-Extra: client
Requires-Dist: requests>=2.21.0; extra == "client"
Requires-Dist: websocket-client>=0.54.0; extra == "client"
Provides-Extra: asyncio-client
Requires-Dist: aiohttp>=3.4; extra == "asyncio-client"
Provides-Extra: docs
Requires-Dist: sphinx; extra == "docs"
